qecp/__init__.py
qecp/qecp.abi3.so
qecp-0.2.3.dist-info/RECORD
qecp-0.2.3.dist-info/WHEEL
qecp-0.2.3.dist-info/METADATA
qecp-0.2.3.dist-info/license_files/LICENSE
