Metadata-Version: 2.1
Name: qecp
Version: 0.2.3
Classifier: Programming Language :: Rust
Classifier: Programming Language :: Python
Classifier: Programming Language :: Python :: 3
Classifier: Programming Language :: Python :: 3 :: Only
Classifier: Programming Language :: Python :: 3.7
Classifier: Programming Language :: Python :: 3.8
Classifier: Programming Language :: Python :: 3.9
Classifier: Programming Language :: Python :: Implementation :: CPython
Classifier: Programming Language :: Python :: Implementation :: PyPy
Classifier: Intended Audience :: Developers
Classifier: Intended Audience :: Information Technology
Classifier: Intended Audience :: System Administrators
Classifier: License :: OSI Approved :: MIT License
Classifier: Operating System :: Unix
Classifier: Operating System :: POSIX :: Linux
Classifier: Environment :: Console
Classifier: Environment :: MacOS X
Classifier: Topic :: Software Development :: Libraries :: Python Modules
Classifier: Topic :: Internet
License-File: LICENSE
Summary: Quantum Error Correction Playground for Surface Code Research
Keywords: QEC,quantum-computing,error-correction,simulation,visualization
Home-Page: https://yuewuo.github.io/QEC-Playground/
Author: Yue Wu <yue.wu@yale.edu>, Namitha Liyanage <namitha.liyanage@yale.edu>, Neil He <neilhe6345@gmail.com>
Author-email: Yue Wu <yue.wu@yale.edu>, Namitha Liyanage <namitha.liyanage@yale.edu>, Neil He <neilhe6345@gmail.com>
License: MIT
Requires-Python: >=3.7
Project-URL: Source Code, https://github.com/yuewuo/QEC-Playground
